HowToMakePackage/Module.py
HowToMakePackage/__init__.py
howtomakepackage-0.1.3.dist-info/METADATA
howtomakepackage-0.1.3.dist-info/WHEEL
howtomakepackage-0.1.3.dist-info/top_level.txt
howtomakepackage-0.1.3.dist-info/RECORD
